<?xml version="1.0" encoding="UTF-8"?>
<questionSet>
  <question>
    <format>1</format>
    <ezid>13570164659530818</ezid>
    <version>1577130962126</version>
    <title><![CDATA[TPC 02-01 (Algo) [LO 2-1]]]></title>
    <type>WK</type>
    <categories>
      <internal_category>
        <catid>1136040857231</catid>
        <title><![CDATA[Learning Objective: 02-01 Explain the concept of sufficiency of a good tax.]]></title>
      </internal_category>
      <internal_category>
        <catid>13570164135571765</catid>
        <title><![CDATA[AACSB: Analytical Thinking]]></title>
      </internal_category>
      <internal_category>
        <catid>1136040723510</catid>
        <title><![CDATA[AICPA: FN Decision Making]]></title>
      </internal_category>
      <internal_category>
        <catid>1136040747176</catid>
        <title><![CDATA[Blooms: Analyze]]></title>
      </internal_category>
      <internal_category>
        <catid>1136040820109</catid>
        <title><![CDATA[Est Time: 20 min.]]></title>
      </internal_category>
      <internal_category>
        <catid>1136040707526</catid>
        <title><![CDATA[AICPA: BB Critical Thinking]]></title>
      </internal_category>
      <internal_category>
        <catid>13570164214530995</catid>
        <title><![CDATA[Topic: Static versus Dynamic Forecasting]]></title>
      </internal_category>
      <internal_category>
        <catid>1136040825672</catid>
        <title><![CDATA[Difficulty: 3 Hard]]></title>
      </internal_category>
      <internal_category>
        <catid>13570164054528189</catid>
        <title><![CDATA[Accessibility: Keyboard Navigation]]></title>
      </internal_category>
      <internal_category>
        <catid>13570164573458385</catid>
        <title><![CDATA[Type: Algorithimic]]></title>
      </internal_category>
      <internal_category>
        <catid>1136040756075</catid>
        <title><![CDATA[Gradable: automatic]]></title>
      </internal_category>
    </categories>
    <randomVariables>
      <pooledRandom>
        <name>a</name>
        <arrayed>true</arrayed>
        <rows>
          <row><![CDATA[6.5,530,5.3,1,2,290,500000,5.3,5.3]]></row>
          <row><![CDATA[6.5,560,5.6,1,2,305,500000,5.6,5.6]]></row>
          <row><![CDATA[6.5,590,5.9,1,2,320,500000,5.9,5.9]]></row>
          <row><![CDATA[6.5,620,6.2,1,2,335,500000,6.2,6.2]]></row>
          <row><![CDATA[6.5,650,6.5,1,2,350,500000,6.5,6.5]]></row>
          <row><![CDATA[6.5,680,6.8,1,2,365,500000,6.8,6.8]]></row>
          <row><![CDATA[6.5,710,7.1,1,2,380,500000,7.1,7.1]]></row>
          <row><![CDATA[6.5,740,7.4,1,2,395,500000,7.4,7.4]]></row>
          <row><![CDATA[6.5,770,7.7,1,2,410,500000,7.7,7.7]]></row>
          <row><![CDATA[6.5,800,8,1,2,425,500000,8,8]]></row>
          <row><![CDATA[6.5,830,8.3,1,2,440,500000,8.3,8.3]]></row>
          <row><![CDATA[6.5,860,8.6,1,2,455,500000,8.6,8.6]]></row>
          <row><![CDATA[6.5,890,8.9,1,2,470,500000,8.9,8.9]]></row>
          <row><![CDATA[6.5,920,9.2,1,2,485,500000,9.2,9.2]]></row>
          <row><![CDATA[6.5,950,9.5,1,2,500,500000,9.5,9.5]]></row>
          <row><![CDATA[6.5,980,9.8,1,2,515,500000,9.8,9.8]]></row>
          <row><![CDATA[6.5,1010,10.1,1,2,530,500000,10.1,10.1]]></row>
          <row><![CDATA[6.5,1040,10.4,1,2,545,500000,10.4,10.4]]></row>
          <row><![CDATA[6.5,1070,10.7,1,2,560,500000,10.7,10.7]]></row>
          <row><![CDATA[6.5,1100,11,1,2,575,500000,11,11]]></row>
          <row><![CDATA[6.5,1130,11.3,1,2,590,500000,11.3,11.3]]></row>
          <row><![CDATA[6.5,1160,11.6,1,2,605,500000,11.6,11.6]]></row>
          <row><![CDATA[6.5,1190,11.9,1,2,620,500000,11.9,11.9]]></row>
          <row><![CDATA[6.5,1220,12.2,1,2,635,500000,12.2,12.2]]></row>
          <row><![CDATA[6.5,1250,12.5,1,2,650,500000,12.5,12.5]]></row>
        </rows>
      </pooledRandom>
    </randomVariables>
    <questionProperties>
      <property name="pageTag" type="string" value="" />
      <property name="customType" type="string" value="" />
      <property name="completeIncompleteGrading" type="string" value="false" />
      <property name="instructor_info" type="string" value="" />
      <property name="forceManualScoring" type="string" value="automatic" />
      <property name="problemSolution" type="string" value="" />
      <property name="audioPlayerPosition" type="string" value="above" />
      <property name="attached_media" type="string" value="" />
      <property name="useCommonFeedback" type="string" value="true" />
      <property name="aggregatedGrading" type="string" value="false" />
    </questionProperties>
    <worksheet>
      <stem><![CDATA[<p>Jurisdiction B&#8217;s tax system consists of a {{[a(1)]:#,###.0}} percent general sales tax on retail goods and selected services. Over the past decade, the average annual volume of sales subject to this tax was ${{[a(2)]:#,###}} million. The jurisdiction needs to increase its tax revenues by approximately ${{[a(3)]:#,###.0}} million each year to finance its spending programs. The taxing authorities are considering two alternatives: a {{[a(4)]:#,###}} percent increase in the sales tax rate or a new {{[a(5)]:#,###}} percent tax on the net income of corporations doing business in the jurisdiction. Based on recent economic data, the annual net income subject to the new tax would be ${{[a(6)]:#,###}} million. However, the jurisdiction would have to create a new agency responsible for enforcing and collecting the income tax. The estimated annual cost of the agency is ${{[a(7)]:#,###}}. Jurisdiction B borders four other taxing jurisdictions, all of which have a general sales tax and two of which have a corporate income tax.<br>
&nbsp;</p>

<p><b>1. </b>Based on a static forecast, how much incremental revenue would Jurisdiction B raise under each alternative? <span style=" color: #b11111;"><b>(Enter your answers in millions rounded to 1 decimal place.)</b></span><br>
<br>
__new__</p>]]></stem>
      <commonFeedback><![CDATA[<ol style=" margin-top: 0px; font-weight: bold; padding-left: 20px;" start="1">
	<li style=" text-align: left;"><span style=" font-weight: normal;">Based on a static forecast, a {{[a(4)]:#,###}} percent increase in the sales tax rate would increase Jurisdiction B&#8217;s annual revenue by ${{[a(3)]:#,###.0}} million. A new {{[a(5)]:#,###}} percent corporate income tax would also increase revenue by ${{[a(8)]:#,###.0}} million ({{[a(5)]:#,###}} percent of a ${{[a(6)]:#,###}} million tax base less ${{[a(7)]:#,###}} cost of the new agency).</span></li>
</ol>]]></commonFeedback>
      <answers>
        <externalAnswer>
          <name><![CDATA[new]]></name>
          <weight>2</weight>
          <answerProperties>
            <property name="identifier" type="string" value="common/accountingtool/1.0/atinit.html" />
            <property name="customType" type="string" value="Worksheet" />
            <property name="completeIncompleteGrading" type="string" value="false" />
            <property name="width" type="string" value="300" />
            <property name="palette" type="string" value="" />
            <property name="state" type="string" value="&quot;}:&quot;n&quot;ioptriscdeb_ta,&quot;{}&quot;:62&quot;_],[0&quot;:67&quot;_l,ul:n1&quot;_5,&quot;llnu&quot;:26&quot;_},:{2&quot;_3,&quot;seal:ft&quot;behalpwAhosS&quot;ie,lsfa&quot;:42&quot;_1,:-0&quot;_5,&quot;-1&quot;:24&quot;_1,:-1&quot;_3,&quot;:05&quot;&quot;_0,&quot;:_4,&quot;seal:f8&quot;_4,&quot;llnu&quot;:37&quot;_],4}46&quot;:77&quot;_8,11&quot;:34&quot;_[{&quot;:23&quot;_e,ru:t5&quot;_4,&quot;1&quot;leit%20Tew&quot;N&quot;:mena,&quot;}]seal:f7&quot;_4,&quot;:24&quot;_5,&quot;[]&quot;:33&quot;_},6&quot;&quot;6&quot;:c2,&quot;1&quot;&quot;7&quot;:c1,&quot;5&quot;28:&quot;0&quot;&quot;c:{9&quot;_1,&quot;&quot;}23:&quot;2&quot;,&quot;3&quot;&quot;2&quot;:&quot;1&quot;,33:&quot;0&quot;{&quot;&quot;:59&quot;_],}]&quot;}x%3B0p:%20ntdeint-ex&quot;t&quot;:_8,&quot;t&quot;efeLylst:&quot;7&quot;&quot;_},N&quot;IOSTUE&quot;Q&quot;:76&quot;_:{5&quot;_5,&quot;}}&quot;&quot;&quot;:79&quot;_&quot;,onliil&quot;m&quot;:75&quot;_:{0&quot;_3{&quot;&quot;:_2{&quot;&quot;:20&quot;_,{}}r&quot;beumeNylste%20nspoes&quot;r&quot;:_7,&quot;&quot;}htig&quot;r&quot;:68&quot;_e,ru:t3&quot;_4,&quot;N&quot;IOUTOL&quot;S&quot;:76&quot;_:{5&quot;_5,&quot;}}%24&quot;:&quot;1&quot;_8,&quot;:23&quot;_5,&quot;:11&quot;_2,&quot;uetr&quot;:63&quot;_:{5&quot;_5,&quot;Y&quot;NCREUR&quot;C&quot;:73&quot;_:{9&quot;_2,&quot;}}&quot;&quot;&quot;:79&quot;_&quot;,)~(9~a:&quot;5&quot;_7{&quot;&quot;:56&quot;_},&quot;&quot;&quot;:79&quot;_&quot;,:&quot;5&quot;_7{&quot;&quot;:30&quot;_:{2&quot;&quot;_:{0&quot;_2{&quot;},&quot;}:&quot;7&quot;&quot;_},N&quot;IOSTUE&quot;Q&quot;:76&quot;_:{5&quot;_5,&quot;}}&quot;&quot;&quot;:79&quot;_&quot;,ax%20tmecoine%20atorrpcot%20enrcpe2%20w%20neA%20:&quot;5&quot;_7{&quot;&quot;:30&quot;_:{2&quot;&quot;_:{0&quot;_2{&quot;,[}]&quot;}x%3B0p:%20ntdeint-ex&quot;t&quot;:_8,&quot;t&quot;efeLylst:&quot;7&quot;&quot;_},N&quot;IOSTUE&quot;Q&quot;:76&quot;_:{5&quot;_5,&quot;}}&quot;&quot;&quot;:79&quot;_&quot;,onliil&quot;m&quot;:75&quot;_:{0&quot;_3{&quot;&quot;:_2{&quot;&quot;:20&quot;_,{}}r&quot;beumeNylste%20nspoes&quot;r&quot;:_7,&quot;&quot;}htig&quot;r&quot;:68&quot;_e,ru:t3&quot;_4,&quot;N&quot;IOUTOL&quot;S&quot;:76&quot;_:{5&quot;_5,&quot;}}%24&quot;:&quot;1&quot;_8,&quot;:23&quot;_5,&quot;:11&quot;_2,&quot;uetr&quot;:63&quot;_:{5&quot;_5,&quot;Y&quot;NCREUR&quot;C&quot;:73&quot;_:{9&quot;_2,&quot;}}&quot;&quot;&quot;:79&quot;_&quot;,)~(9~a:&quot;5&quot;_7{&quot;&quot;:56&quot;_},&quot;&quot;&quot;:79&quot;_&quot;,:&quot;5&quot;_7{&quot;&quot;:30&quot;_:{2&quot;&quot;_:{0&quot;_2{&quot;},&quot;}:&quot;7&quot;&quot;_},N&quot;IOSTUE&quot;Q&quot;:76&quot;_:{5&quot;_5,&quot;}}&quot;&quot;&quot;:79&quot;_&quot;,ax%20tesal%20she%20tine%20asrenc%20intceer%20p%201&quot;A&quot;:75&quot;_:{0&quot;_3{&quot;&quot;:_2{&quot;&quot;:20&quot;_[{],}}&quot;&quot;&quot;:_7,&quot;%3B&quot;px23:%20htighe%3B%20neno:%20ayplis%20d)%3B29%2023,17,%2021(1gb%20rr:locod-unrokgac&quot;b&quot;:_8,&quot;&quot;}_1&quot;0&quot;:78&quot;_&quot;,e5ad79&quot;%23&quot;:_9,&quot;N&quot;IOSTUE&quot;Q&quot;:76&quot;_:{5&quot;_5,&quot;}}&quot;&quot;&quot;:79&quot;_&quot;,:&quot;5&quot;_7{&quot;&quot;:30&quot;_:{2&quot;&quot;_:{0&quot;_2{&quot;},&quot;}x%3B3p%202t:ghei%20h)%3B29%2023,17,%2021(1gb%20rr:locod-unrokgac%20bx%3B0p:%20ntdeint-ex&quot;t&quot;:_8,&quot;d&quot;oleBylstr%20teeneCylst:&quot;7&quot;&quot;_2,&quot;:16&quot;_},0&quot;0_:&quot;8&quot;_7,&quot;uetr&quot;:10&quot;_&quot;,e5ad79&quot;%23&quot;:_9,&quot;r&quot;teen&quot;c&quot;:68&quot;_&quot;,ONTIESQU:&quot;6&quot;_7{&quot;&quot;:55&quot;_},&quot;}:&quot;9&quot;_7,&quot;e&quot;nuveRel%20taenemcrIn:&quot;5&quot;_7{&quot;&quot;:30&quot;_:{2&quot;&quot;_:{0&quot;_2{&quot;},&quot;}:&quot;7&quot;&quot;_&quot;,x%3B3p%202t:ghei%20h)%3B29%2023,17,%2021(1gb%20rr:locod-unrokgac&quot;b&quot;:_8,&quot;&quot;}e5ad79&quot;%23&quot;:_9,&quot;N&quot;IOSTUE&quot;Q&quot;:76&quot;_:{5&quot;_5,&quot;}}&quot;&quot;&quot;:79&quot;_&quot;,:&quot;5&quot;_7{&quot;&quot;:30&quot;_:{2&quot;&quot;_:{0&quot;_2{&quot;[[&quot;:13&quot;_e,lsfa&quot;:41&quot;_},n&quot;owpDro&quot;d&quot;:27&quot;_1,:-5&quot;_2,&quot;{}&quot;:75&quot;_e,lsfa&quot;:82&quot;_:{8&quot;_2,&quot;&quot;&quot;&quot;:22&quot;_e,lsfa&quot;:35&quot;_e,ru:t6&quot;_3,&quot;{}&quot;:55&quot;_&quot;,leab%20TedtltiUn:&quot;9&quot;_6,&quot;:37&quot;_1,&quot;:38&quot;_5{&quot;:[5&quot;_6{&quot;" />
            <property name="height" type="string" value="100" />
          </answerProperties>
        </externalAnswer>
      </answers>
    </worksheet>
  </question>
  <question>
    <format>1</format>
    <ezid>13570164659530819</ezid>
    <version>1577130962126</version>
    <title><![CDATA[TPC 02-01 (Static) [LO 2-1]]]></title>
    <type>WK</type>
    <categories>
      <internal_category>
        <catid>1136040857231</catid>
        <title><![CDATA[Learning Objective: 02-01 Explain the concept of sufficiency of a good tax.]]></title>
      </internal_category>
      <internal_category>
        <catid>13570164135571765</catid>
        <title><![CDATA[AACSB: Analytical Thinking]]></title>
      </internal_category>
      <internal_category>
        <catid>1136040723510</catid>
        <title><![CDATA[AICPA: FN Decision Making]]></title>
      </internal_category>
      <internal_category>
        <catid>1136040747176</catid>
        <title><![CDATA[Blooms: Analyze]]></title>
      </internal_category>
      <internal_category>
        <catid>1136040820109</catid>
        <title><![CDATA[Est Time: 20 min.]]></title>
      </internal_category>
      <internal_category>
        <catid>1136040707526</catid>
        <title><![CDATA[AICPA: BB Critical Thinking]]></title>
      </internal_category>
      <internal_category>
        <catid>13570164214530995</catid>
        <title><![CDATA[Topic: Static versus Dynamic Forecasting]]></title>
      </internal_category>
      <internal_category>
        <catid>1136040825672</catid>
        <title><![CDATA[Difficulty: 3 Hard]]></title>
      </internal_category>
      <internal_category>
        <catid>13570164054528189</catid>
        <title><![CDATA[Accessibility: Keyboard Navigation]]></title>
      </internal_category>
      <internal_category>
        <catid>13570164528935313</catid>
        <title><![CDATA[Type: Static]]></title>
      </internal_category>
      <internal_category>
        <catid>1136040756075</catid>
        <title><![CDATA[Gradable: automatic]]></title>
      </internal_category>
    </categories>
    <questionProperties>
      <property name="pageTag" type="string" value="" />
      <property name="customType" type="string" value="" />
      <property name="completeIncompleteGrading" type="string" value="false" />
      <property name="hm_points" type="BigDecimal" value="10.00" />
      <property name="instructor_info" type="string" value="" />
      <property name="forceManualScoring" type="string" value="automatic" />
      <property name="problemSolution" type="string" value="" />
      <property name="audioPlayerPosition" type="string" value="above" />
      <property name="attached_media" type="string" value="" />
      <property name="useCommonFeedback" type="string" value="true" />
      <property name="aggregatedGrading" type="string" value="false" />
    </questionProperties>
    <worksheet>
      <stem><![CDATA[<p>Jurisdiction B&#8217;s tax system consists of a 6.5 percent general sales tax on retail goods and selected services. Over the past decade, the average annual volume of sales subject to this tax was $500 million. The jurisdiction needs to increase its tax revenues by approximately $5 million each year to finance its spending programs. The taxing authorities are considering two alternatives: a 1 percent increase in the sales tax rate or a new 2 percent tax on the net income of corporations doing business in the jurisdiction. Based on recent economic data, the annual net income subject to the new tax would be $275 million. However, the jurisdiction would have to create a new agency responsible for enforcing and collecting the income tax. The estimated annual cost of the agency is $500,000. Jurisdiction B borders four other taxing jurisdictions, all of which have a general sales tax and two of which have a corporate income tax.<br>
&nbsp;</p>

<p><b>1. </b>Based on a static forecast, how much incremental revenue would Jurisdiction B raise under each alternative?<span style=" color: #b11111;"><b> (Enter your answers in millions.)</b></span><br>
<br>
__new__</p>]]></stem>
      <commonFeedback><![CDATA[<ol start="1" style=" margin-top: 0px; font-weight: bold; padding-left: 20px;">
	<li style=" text-align: left;"><span style=" font-weight: normal;">Based on a static forecast, a 1 percent increase in the sales tax rate would increase Jurisdiction B&#8217;s annual revenue by $5 million. A new 2 percent corporate income tax would also increase revenue by $5 million (2 percent of a $275 million tax base less $500,000 cost of the new agency).</span></li>
</ol>]]></commonFeedback>
      <answers>
        <externalAnswer>
          <name><![CDATA[new]]></name>
          <weight>2</weight>
          <answerProperties>
            <property name="identifier" type="string" value="common/accountingtool/1.0/atinit.html" />
            <property name="customType" type="string" value="Worksheet" />
            <property name="completeIncompleteGrading" type="string" value="false" />
            <property name="width" type="string" value="300" />
            <property name="palette" type="string" value="" />
            <property name="state" type="string" value="}&quot;&quot;&quot;:ontiipcres_dab&quot;t},:{2&quot;_6,&quot;0]:[7&quot;_6,&quot;llnu&quot;:51&quot;_l,ul:n6&quot;_2,&quot;{}&quot;:32&quot;_e,lsfa&quot;:etabphAlowShis,&quot;seal:f2&quot;_4,&quot;-1&quot;:50&quot;_1,:-4&quot;_2,&quot;-1&quot;:31&quot;_0,&quot;:_5,&quot;:04&quot;&quot;_e,lsfa&quot;:48&quot;_l,ul:n7&quot;_3,&quot;}]53:47&quot;_7,&quot;15:14&quot;_3{&quot;:[3&quot;_2,&quot;uetr&quot;:45&quot;_&quot;,e1tlTiw%20Ne:&quot;e&quot;am&quot;n],e}lsfa&quot;:47&quot;_2,&quot;:54&quot;_],:[3&quot;_3,&quot;&quot;}62:&quot;2&quot;&quot;c&quot;,69:&quot;1&quot;&quot;c&quot;,80&quot;2&quot;:c0{&quot;&quot;:19&quot;_},3&quot;&quot;2&quot;:&quot;2&quot;,23:&quot;1&quot;,&quot;3&quot;&quot;3&quot;:&quot;0:{9&quot;_5,&quot;]]}}%3B&quot;px%200t:ennd-ixtte:&quot;8&quot;&quot;_&quot;,ftLelety&quot;s&quot;:_7,&quot;&quot;}ONTIESQU:&quot;6&quot;_7{&quot;&quot;:55&quot;_},&quot;}:&quot;9&quot;_7,&quot;n&quot;iollmi:&quot;5&quot;_7{&quot;&quot;:30&quot;_:{2&quot;&quot;_:{0&quot;_2{&quot;},&quot;}ermbNulety%20sseonspre:&quot;7&quot;&quot;_},uetr&quot;:43&quot;_&quot;,ONTILUSO:&quot;6&quot;_7{&quot;&quot;:55&quot;_},&quot;}&quot;%24&quot;:81&quot;_2,&quot;:53&quot;_e,ru:t3&quot;_6{&quot;&quot;:55&quot;_&quot;,CYENRRCU:&quot;3&quot;_7{&quot;&quot;:29&quot;_},&quot;}:&quot;9&quot;_7,&quot;5&quot;:&quot;5&quot;_7{&quot;&quot;:56&quot;_},&quot;&quot;&quot;:79&quot;_&quot;,:&quot;5&quot;_7{&quot;&quot;:30&quot;_:{2&quot;&quot;_:{0&quot;_2{&quot;},}}N&quot;IOSTUE&quot;Q&quot;:76&quot;_:{5&quot;_5,&quot;}}&quot;&quot;&quot;:79&quot;_&quot;,ax%20tmecoine%20atorrpcot%20enrcpe2%20w%20neA%20:&quot;5&quot;_7{&quot;&quot;:30&quot;_:{2&quot;&quot;_:{0&quot;_2{&quot;,[}]&quot;}x%3B0p:%20ntdeint-ex&quot;t&quot;:_8,&quot;t&quot;efeLylst:&quot;7&quot;&quot;_},N&quot;IOSTUE&quot;Q&quot;:76&quot;_:{5&quot;_5,&quot;}}&quot;&quot;&quot;:79&quot;_&quot;,onliil&quot;m&quot;:75&quot;_:{0&quot;_3{&quot;&quot;:_2{&quot;&quot;:20&quot;_,{}}r&quot;beumeNylste%20nspoes&quot;r&quot;:_7,&quot;e}ru:t3&quot;_4,&quot;N&quot;IOUTOL&quot;S&quot;:76&quot;_:{5&quot;_5,&quot;}}%24&quot;:&quot;1&quot;_8,&quot;:23&quot;_5,&quot;uetr&quot;:63&quot;_:{5&quot;_5,&quot;Y&quot;NCREUR&quot;C&quot;:73&quot;_:{9&quot;_2,&quot;}}&quot;&quot;&quot;:79&quot;_&quot;,&quot;5&quot;:75&quot;_:{6&quot;_5,&quot;&quot;}:&quot;9&quot;_7,&quot;&quot;&quot;&quot;:75&quot;_:{0&quot;_3{&quot;&quot;:_2{&quot;&quot;:20&quot;_,{}}&quot;}ONTIESQU:&quot;6&quot;_7{&quot;&quot;:55&quot;_},&quot;}:&quot;9&quot;_7,&quot;x&quot;tas%20lesae%20thn%20%20iseeacrint%20enrcpe1%20A%20:&quot;5&quot;_7{&quot;&quot;:30&quot;_:{2&quot;&quot;_:{0&quot;_2{&quot;,[}]&quot;}e%3Bon%20ny:laspdi%3B%20e5ad79%20%23r:locod-unrokgac&quot;b&quot;:_8,&quot;&quot;}_1&quot;0&quot;:78&quot;_&quot;,e5ad79&quot;%23&quot;:_9,&quot;N&quot;IOSTUE&quot;Q&quot;:76&quot;_:{5&quot;_5,&quot;}}&quot;&quot;&quot;:79&quot;_&quot;,:&quot;5&quot;_7{&quot;&quot;:30&quot;_:{2&quot;&quot;_:{0&quot;_2{&quot;},&quot;}5%3Bde9a%237:%20orol-cndougrckba%3B%20px%200t:ennd-ixtte:&quot;8&quot;&quot;_&quot;,ldBolety%20serntCelety&quot;s&quot;:_7,&quot;2&quot;:&quot;6&quot;_1,&quot;&quot;}_0&quot;0&quot;:78&quot;_e,ru:t0&quot;_1,&quot;5&quot;de9a%237:&quot;9&quot;&quot;_&quot;,erntce:&quot;8&quot;_6,&quot;N&quot;IOSTUE&quot;Q&quot;:76&quot;_:{5&quot;_5,&quot;}}&quot;&quot;&quot;:79&quot;_&quot;,ueenev%20Ralntmerenc&quot;I&quot;:75&quot;_:{0&quot;_3{&quot;&quot;:_2{&quot;&quot;:20&quot;_,{}}&quot;&quot;&quot;:_7,&quot;%3B&quot;e5ad79%20%23r:locod-unrokgac&quot;b&quot;:_8,&quot;&quot;}e5ad79&quot;%23&quot;:_9,&quot;N&quot;IOSTUE&quot;Q&quot;:76&quot;_:{5&quot;_5,&quot;}}&quot;&quot;&quot;:79&quot;_&quot;,:&quot;5&quot;_7{&quot;&quot;:30&quot;_:{2&quot;&quot;_:{0&quot;_2{&quot;[[&quot;:13&quot;_e,lsfa&quot;:41&quot;_},n&quot;owpDro&quot;d&quot;:27&quot;_1,:-5&quot;_2,&quot;{}&quot;:75&quot;_e,lsfa&quot;:82&quot;_:{8&quot;_2,&quot;&quot;&quot;&quot;:22&quot;_e,lsfa&quot;:35&quot;_e,ru:t6&quot;_3,&quot;{}&quot;:55&quot;_&quot;,leab%20TedtltiUn:&quot;9&quot;_6,&quot;:37&quot;_1,&quot;:38&quot;_5{&quot;:[5&quot;_6{&quot;" />
            <property name="height" type="string" value="100" />
          </answerProperties>
        </externalAnswer>
      </answers>
    </worksheet>
  </question>
</questionSet>

